Metadata-Version: 2.1
Name: gspm
Version: 0.1.36
Summary: A Command Line Utility to Assist in Managing your GODOT projects.
Home-page: https://pypi.org/project/gspm/
Download-URL: https://gitlab.com/retro-coder/commodore/kick-assembler-vscode-ext
Author: Paul Hocker
Author-email: paul@spocker.net
License: MIT
Classifier: Development Status :: 2 - Pre-Alpha
Classifier: License :: OSI Approved :: MIT License
Classifier: Natural Language :: English
Classifier: Operating System :: MacOS
Classifier: Operating System :: Microsoft :: Windows
Classifier: Operating System :: POSIX :: Linux
Classifier: Programming Language :: Python :: 3.6
Classifier: Programming Language :: Python :: 3.5
Classifier: Programming Language :: Python :: 3.4
Classifier: Topic :: Utilities
Classifier: Topic :: Games/Entertainment
Classifier: Environment :: Console
License-File: LICENSE.md
License-File: AUTHORS.md
